{
  "wanted_people": [
    {
      "name": {
        "last": "ALFORD",
        "first": "BRYAN",
        "middle": "EDGAR"
      },
      "address": {
        "street": "67 SPANISH MOSS ROAD",
        "cityStateZip": "RIDGELAND, SC 29936"
      },
      "raceGender": "N-White, Non-Hisp / Male",
      "race": "W",
      "sex": "M",
      "dob": "10/15/70",
      "age": "53",
      "height": "5'07\"",
      "weight": "163",
      "bookingDate": "09:43:30 03/21/24",
      "bookingNumber": "46777",
      "warrants": [
        {
          "offenses": [
            "Family Court Bench Warrant"
          ],
          "iceHold": "",
          "mugshotImage": "http://mugshots.bcgov.net/images/80/221480/24032109575400.jpeg",
          "arrestAgency": "Beaufort County Sheriff's Ofc",
          "arrestOfficer": "Parnell, R"
        }
      ]
    },
    {
      "name": {
        "last": "AMMONS",
        "first": "MORGAN",
        "middle": "PHILIPPE FLYNN"
      },
      "address": {
        "street": "124 MURFIELD DR",
        "cityStateZip": "Bluffton, SC 29909"
      },
      "raceGender": "N-White, Non-Hisp / Male",
      "race": "W",
      "sex": "M",
      "dob": "07/04/00",
      "age": "23",
      "height": "5'08\"",
      "weight": "121",
      "bookingDate": "11:22:11 03/19/24",
      "bookingNumber": "46735",
      "warrants": [
        {
          "offenses": [
            "CSCMinor/sodomy(oral/anal)(<11)"
          ],
          "iceHold": "",
          "mugshotImage": "http://mugshots.bcgov.net/images/50/175150/24031911405100.jpeg",
          "arrestAgency": "Beaufort County Sheriff's Ofc",
          "arrestOfficer": "Perkins, M"
        }
      ]
    },
    {
      "name": {
        "last": "BENNETT",
        "first": "DESARAI",
        "middle": ""
      },
      "address": {
        "street": "325 Ambrose Run Apt 507",
        "cityStateZip": "City of Bft, SC 29906"
      },
      "raceGender": "N-Black, Non-Hisp / Female",
      "race": "B",
      "sex": "F",
      "dob": "07/02/01",
      "age": "22",
      "height": "5'04\"",
      "weight": "120",
      "bookingDate": "07:43:11 03/19/24",
      "bookingNumber": "46731",
      "warrants": [
        {
          "offenses": [
            "ACCESSORY BEFORE THE FACT TO A FELONY; GENERAL PROVISION (VIOLENT IF VIOLENT FELONY)",
            "CRIMINAL CONSPIRACY; COMMON LAW CONSPIRACY DEFINED",
            "FILING A FALSE POLICE REPORT OF A FELONY VIOLATION"
          ],
          "iceHold": "",
          "mugshotImage": "http://mugshots.bcgov.net/images/68/79668/24031908270300.jpeg",
          "arrestAgency": "Beaufort PD",
          "arrestOfficer": "Martinez, Es"
        }
      ]
    },
    {
      "name": {
        "last": "CARPENTIERI",
        "first": "MELISSA",
        "middle": "ANN"
      },
      "address": {
        "street": "15 DEVONWOOD DR",
        "cityStateZip": "Bluffton, SC 29910"
      },
      "raceGender": "N-White, Non-Hisp / Female",
      "race": "W",
      "sex": "F",
      "dob": "07/04/85",
      "age": "38",
      "height": "5'08\"",
      "weight": "145",
      "bookingDate": "07:55:32 03/19/24",
      "bookingNumber": "46732",
      "warrants": [
        {
          "offenses": [
            "Family Court Bench Warrant"
          ],
          "iceHold": "",
          "mugshotImage": "http://mugshots.bcgov.net/images/78/21278/24031908165900.jpeg",
          "arrestAgency": "Beaufort County Sheriff's Ofc",
          "arrestOfficer": "Seronka, Chad"
        }
      ]
    },
    {
      "name": {
        "last": "COOTS",
        "first": "APRIL",
        "middle": "DAWN"
      },
      "address": {
        "street": "30 VINE LANE",
        "cityStateZip": "Twn of Bluffton, SC 29910"
      },
      "raceGender": "N-White, Non-Hisp / Female",
      "race": "W",
      "sex": "F",
      "dob": "10/30/81",
      "age": "42",
      "height": "5'07\"",
      "weight": "135",
      "bookingDate": "18:27:34 03/20/24",
      "bookingNumber": "46764",
      "warrants": [
        {
          "offenses": [
            "DRIVING UNDER SUSPENSION; LICENSE NOT SUSPENDED FOR DUI - 1ST OFFENSE",
            "UNINSURED MOTOR VEHICLE"
          ],
          "iceHold": "",
          "mugshotImage": "http://mugshots.bcgov.net/images/29/36729/24032018331800.jpeg",
          "arrestAgency": "South Carolina Highway Patrol",
          "arrestOfficer": "CUATA"
        }
      ]
    },
    {
      "name": {
        "last": "CROSS",
        "first": "MARCUS",
        "middle": "DANIEL"
      },
      "address": {
        "street": "3128 CLYDESDALE CIRCLE",
        "cityStateZip": "Beaufort, SC 29906"
      },
      "raceGender": "N-Black, Non-Hisp / Male",
      "race": "B",
      "sex": "M",
      "dob": "05/12/79",
      "age": "44",
      "height": "5'10\"",
      "weight": "140",
      "bookingDate": "03:43:30 03/20/24",
      "bookingNumber": "46750",
      "warrants": [
        {
          "offenses": [
            "Marij: Simple Possession"
          ],
          "iceHold": "",
          "mugshotImage": "http://mugshots.bcgov.net/images/03/272603/24032004384200.jpeg",
          "arrestAgency": "Bluffton PD",
          "arrestOfficer": "Young, A"
        }
      ]
    },
    {
      "name": {
        "last": "FRAZIER",
        "first": "EUGENE",
        "middle": ""
      },
      "address": {
        "street": "HOMELESS",
        "cityStateZip": "BEAUFORT, SC 29902"
      },
      "raceGender": "N-Black, Non-Hisp / Male",
      "race": "B",
      "sex": "M",
      "dob": "05/27/56",
      "age": "67",
      "height": "5'11\"",
      "weight": "160",
      "bookingDate": "21:47:28 03/18/24",
      "bookingNumber": "46726",
      "warrants": [
        {
          "offenses": [
            "Appearing Drunk on Streets",
            "SEX OFFENDER REGISTRY VIOLATION; FAIL TO REGISTER - 1ST OFFENSE"
          ],
          "iceHold": "",
          "mugshotImage": "http://mugshots.bcgov.net/images/24/3824/24031821412100.jpeg",
          "arrestAgency": "Beaufort PD",
          "arrestOfficer": "Humphries, M"
        }
      ]
    },
    {
      "name": {
        "last": "GONZELEZ",
        "first": "KROSS",
        "middle": "JESUS"
      },
      "address": {
        "street": "HOMELESS",
        "cityStateZip": "BEAUFORT, SC 29906"
      },
      "raceGender": "H-White/Latin, Hispanic / Male",
      "race": "L",
      "sex": "M",
      "dob": "12/19/00",
      "age": "23",
      "height": "5'04\"",
      "weight": "130",
      "bookingDate": "14:45:53 03/20/24",
      "bookingNumber": "46757",
      "warrants": [
        {
          "offenses": [
            "Trespassing",
            "SHOPLIFTING/VALUE 2000 OR LESS ENHANCEMENT PER 16-01-0057"
          ],
          "iceHold": "",
          "mugshotImage": "http://mugshots.bcgov.net/images/02/243602/24032015400600.jpeg",
          "arrestAgency": "Beaufort PD",
          "arrestOfficer": "Zielinski, R"
        }
      ]
    },
    {
      "name": {
        "last": "GREGORY",
        "first": "JIMMY",
        "middle": ""
      },
      "address": {
        "street": "303 FOREST DRIVE",
        "cityStateZip": "RIDGELAND, SC 29936"
      },
      "raceGender": "N-Black, Non-Hisp / Male",
      "race": "B",
      "sex": "M",
      "dob": "10/13/60",
      "age": "63",
      "height": "6'00\"",
      "weight": "180",
      "bookingDate": "02:56:20 03/21/24",
      "bookingNumber": "46773",
      "warrants": [
        {
          "offenses": [
            "SHOPLIFTING",
            "PETIT OR SIMPLE LARCENY -$2,000 OR LESS",
            "TRESPASSING",
            "ENTERING PREMISES AFTER WARNING OR REFUSING TO LEAVE ON REQUEST",
            "PETIT OR SIMPLE LARCENY -$2,000 OR LESS"
          ],
          "iceHold": "",
          "mugshotImage": "http://mugshots.bcgov.net/images/41/52041/24032104420100.jpeg",
          "arrestAgency": "Beaufort County Sheriff's Ofc",
          "arrestOfficer": "Cochenour, A"
        }
      ]
    },
    {
      "name": {
        "last": "HERNANDEZ HERNANDEZ",
        "first": "MAXIMINO",
        "middle": ""
      },
      "address": {
        "street": "60 WILWOOD LANE UNIT 201",
        "cityStateZip": "RIDGELAND, SC 29936"
      },
      "raceGender": "H-White/Latin, Hispanic / Male",
      "race": "L",
      "sex": "M",
      "dob": "12/27/80",
      "age": "43",
      "height": "5'08\"",
      "weight": "150",
      "bookingDate": "07:50:45 03/20/24",
      "bookingNumber": "46752",
      "warrants": [
        {
          "offenses": [
            "DRIVING WITHOUT A LICENSE OR POSSESSION OF MORE THAN ONE DRIVERS LICENSE"
          ],
          "iceHold": "",
          "mugshotImage": "http://mugshots.bcgov.net/images/03/293103/24032008115000.jpeg",
          "arrestAgency": "Beaufort County Sheriff's Ofc",
          "arrestOfficer": "Meehan, R"
        }
      ]
    },
    {
      "name": {
        "last": "INFANTE VASSURA",
        "first": "MAURICIO",
        "middle": "ENRIQUE"
      },
      "address": {
        "street": "",
        "cityStateZip": ","
      },
      "raceGender": "H-White/Latin, Hispanic / Male",
      "race": "L",
      "sex": "M",
      "dob": "07/05/88",
      "age": "35",
      "height": "'  \"",
      "weight": "0",
      "bookingDate": "13:29:45 03/21/24",
      "bookingNumber": "46779",
      "warrants": [
        {
          "offenses": [
            "DRIVING WITHOUT A LICENSE OR POSSESSION OF MORE THAN ONE DRIVERS LICENSE"
          ],
          "iceHold": "",
          "mugshotImage": "http://mugshots.bcgov.net/images/48/363448/24032113320100.jpeg",
          "arrestAgency": "South Carolina Highway Patrol",
          "arrestOfficer": "CUATA, C"
        }
      ]
    },
    {
      "name": {
        "last": "JAMES",
        "first": "HILDA",
        "middle": "CICRO"
      },
      "address": {
        "street": "13 KITTIES LANDING RD",
        "cityStateZip": "BLUFFTON, SC 29910"
      },
      "raceGender": "H-White/Latin, Hispanic / Female",
      "race": "L",
      "sex": "F",
      "dob": "12/24/60",
      "age": "63",
      "height": "5'08\"",
      "weight": "150",
      "bookingDate": "18:43:35 03/20/24",
      "bookingNumber": "46763",
      "warrants": [
        {
          "offenses": [
            "PUBLIC DISORDERLY CONDUCT"
          ],
          "iceHold": "",
          "mugshotImage": "http://mugshots.bcgov.net/images/58/295458/24032106193700.jpeg",
          "arrestAgency": "Beaufort County Sheriff's Ofc",
          "arrestOfficer": "Clouse, J"
        }
      ]
    },
    {
      "name": {
        "last": "JONES",
        "first": "DARCIE",
        "middle": "LYNN"
      },
      "address": {
        "street": "399 PINELAND ESTATES",
        "cityStateZip": "PINELAND, SC 29934"
      },
      "raceGender": "N-White, Non-Hisp / Female",
      "race": "W",
      "sex": "F",
      "dob": "10/16/82",
      "age": "41",
      "height": "5'05\"",
      "weight": "175",
      "bookingDate": "01:28:27 03/21/24",
      "bookingNumber": "46770",
      "warrants": [
        {
          "offenses": [
            "DRIVING UNDER THE INFLUENCE (DUI)"
          ],
          "iceHold": "",
          "mugshotImage": "http://mugshots.bcgov.net/images/56/70556/24032102124800.jpeg",
          "arrestAgency": "Beaufort County Sheriff's Ofc",
          "arrestOfficer": "Erickson, M"
        }
      ]
    },
    {
      "name": {
        "last": "JONES",
        "first": "JAMES",
        "middle": "DEQUAN"
      },
      "address": {
        "street": "215 MARSHLAND RD",
        "cityStateZip": "HILTON HEAD ISL, SC 29926"
      },
      "raceGender": "N-Black, Non-Hisp / Male",
      "race": "B",
      "sex": "M",
      "dob": "11/16/89",
      "age": "34",
      "height": "5'10\"",
      "weight": "210",
      "bookingDate": "22:41:15 03/20/24",
      "bookingNumber": "46769",
      "warrants": [
        {
          "offenses": [
            "DRUGS/FENTANYL, POSSESSION OF MORE THAN 2 GRAINS",
            "CrackCocaine:PWITD"
          ],
          "iceHold": "",
          "mugshotImage": "http://mugshots.bcgov.net/images/57/34757/24032022521100.jpeg",
          "arrestAgency": "Beaufort County Sheriff's Ofc",
          "arrestOfficer": "Aaron, M"
        }
      ]
    },
    {
      "name": {
        "last": "KINCADE",
        "first": "JAYDEN",
        "middle": ""
      },
      "address": {
        "street": "5 SHIPWRECK LN",
        "cityStateZip": "St Helena Islan, SC 29920"
      },
      "raceGender": "N-Black, Non-Hisp / Male",
      "race": "B",
      "sex": "M",
      "dob": "03/16/04",
      "age": "20",
      "height": "5'07\"",
      "weight": "180",
      "bookingDate": "03:06:43 03/21/24",
      "bookingNumber": "46774",
      "warrants": [
        {
          "offenses": [
            "Marij/Poss 28g<10gr<Hash 1st"
          ],
          "iceHold": "",
          "mugshotImage": "http://mugshots.bcgov.net/images/87/363387/",
          "arrestAgency": "Beaufort County Sheriff's Ofc",
          "arrestOfficer": "Weaver, J"
        }
      ]
    },
    {
      "name": {
        "last": "KOCHENDERFER",
        "first": "BENJAMIN",
        "middle": "JOSEPH"
      },
      "address": {
        "street": "100 KENSINGTON BLVD # 403; THE ESTATES AT WESTBURY 403",
        "cityStateZip": "Bluffton, SC 29910"
      },
      "raceGender": "N-White, Non-Hisp / Male",
      "race": "W",
      "sex": "M",
      "dob": "06/09/76",
      "age": "47",
      "height": "5'10\"",
      "weight": "325",
      "bookingDate": "01:37:40 03/21/24",
      "bookingNumber": "46771",
      "warrants": [
        {
          "offenses": [
            "PUBLIC DISORDERLY CONDUCT"
          ],
          "iceHold": "",
          "mugshotImage": "http://mugshots.bcgov.net/images/90/174590/24032104005900.jpeg",
          "arrestAgency": "Beaufort County Sheriff's Ofc",
          "arrestOfficer": "Clouse, M"
        }
      ]
    },
    {
      "name": {
        "last": "LUDAWAY",
        "first": "DERRICK",
        "middle": "ANTHONY"
      },
      "address": {
        "street": "4921 BLUFFTON PKWY #767",
        "cityStateZip": "Bluffton, SC 29910"
      },
      "raceGender": "N-Black, Non-Hisp / Male",
      "race": "B",
      "sex": "M",
      "dob": "02/10/79",
      "age": "45",
      "height": "6'00\"",
      "weight": "235",
      "bookingDate": "09:56:03 03/19/24",
      "bookingNumber": "46741",
      "warrants": [
        {
          "offenses": [
            "POSS. OF 28G (1 OZ) OR LESS OF MARIJUANA"
          ],
          "iceHold": "",
          "mugshotImage": "http://mugshots.bcgov.net/images/69/49069/",
          "arrestAgency": "Beaufort County Sheriff's Ofc",
          "arrestOfficer": "Partridge, C"
        }
      ]
    },
    {
      "name": {
        "last": "MANIGO",
        "first": "RUSSELL",
        "middle": "TRENT"
      },
      "address": {
        "street": "773 Newberg Ave",
        "cityStateZip": "Macon, GA"
      },
      "raceGender": "N-Black, Non-Hisp / Male",
      "race": "B",
      "sex": "M",
      "dob": "09/22/92",
      "age": "31",
      "height": "6'02\"",
      "weight": "163",
      "bookingDate": "18:07:28 03/19/24",
      "bookingNumber": "46740",
      "warrants": [
        {
          "offenses": [
            "DOMESTIC VIOLENCE 2ND DEGREE",
            "FUG. FROM JUSTICE WARRANT; NON-CRIM. HOLD FUG. MAX. 20 DAYS. GOV. OFC."
          ],
          "iceHold": "",
          "mugshotImage": "http://mugshots.bcgov.net/images/85/19785/24031919595600.jpeg",
          "arrestAgency": "Beaufort County Sheriff's Ofc",
          "arrestOfficer": "Perkins, M"
        }
      ]
    },
    {
      "name": {
        "last": "MARTINI",
        "first": "JULIANE",
        "middle": "LOUISE"
      },
      "address": {
        "street": "133 HARVEST CIR",
        "cityStateZip": "BLUFFTON, SC 29910"
      },
      "raceGender": "N-White, Non-Hisp / Female",
      "race": "W",
      "sex": "F",
      "dob": "06/05/51",
      "age": "72",
      "height": "5'09\"",
      "weight": "190",
      "bookingDate": "22:28:57 03/19/24",
      "bookingNumber": "46744",
      "warrants": [
        {
          "offenses": [
            "TRESPASSING"
          ],
          "iceHold": "",
          "mugshotImage": "http://mugshots.bcgov.net/images/59/139459/24031922370800.jpeg",
          "arrestAgency": "Beaufort County Sheriff's Ofc",
          "arrestOfficer": "Walker, D"
        }
      ]
    },
    {
      "name": {
        "last": "MILLER",
        "first": "RODNEY",
        "middle": "EARL"
      },
      "address": {
        "street": "3038 MINK POINT BLVD",
        "cityStateZip": "BEAUFORT, SC 29902 5813"
      },
      "raceGender": "N-Black, Non-Hisp / Male",
      "race": "B",
      "sex": "M",
      "dob": "07/15/99",
      "age": "24",
      "height": "6'01\"",
      "weight": "250",
      "bookingDate": "02:12:47 03/21/24",
      "bookingNumber": "46772",
      "warrants": [
        {
          "offenses": [
            "DRIVING UNDER SUSPENSION; LICENSE NOT SUSPENDED FOR DUI - 1ST OFFENSE"
          ],
          "iceHold": "",
          "mugshotImage": "http://mugshots.bcgov.net/images/11/16311/24032102251400.jpeg",
          "arrestAgency": "South Carolina Highway Patrol",
          "arrestOfficer": "DEANER"
        }
      ]
    },
    {
      "name": {
        "last": "MILTON",
        "first": "CURTIS",
        "middle": "D'ANDRE"
      },
      "address": {
        "street": "100 HELMSMAN WAY #110",
        "cityStateZip": "Hilton Head Isl, SC 29928"
      },
      "raceGender": "N-Black, Non-Hisp / Male",
      "race": "B",
      "sex": "M",
      "dob": "10/06/92",
      "age": "31",
      "height": "6'02\"",
      "weight": "163",
      "bookingDate": "22:55:21 03/20/24",
      "bookingNumber": "46768",
      "warrants": [
        {
          "offenses": [
            "POSS OF OTHER CONTROLLED SUB IN SCHED I TO V",
            "POSS. OF 28G (1 OZ) OR LESS OF MARIJUANA"
          ],
          "iceHold": "",
          "mugshotImage": "http://mugshots.bcgov.net/images/45/2345/24032022572400.jpeg",
          "arrestAgency": "Beaufort County Sheriff's Ofc",
          "arrestOfficer": "Aaron, M"
        }
      ]
    },
    {
      "name": {
        "last": "MOULTRIE",
        "first": "MALIK",
        "middle": "LAMOND"
      },
      "address": {
        "street": "1842 TRASK PKWY",
        "cityStateZip": "Lobeco, SC 29940"
      },
      "raceGender": "N-Black, Non-Hisp / Male",
      "race": "B",
      "sex": "M",
      "dob": "09/02/96",
      "age": "27",
      "height": "6'01\"",
      "weight": "150",
      "bookingDate": "17:48:05 03/19/24",
      "bookingNumber": "46739",
      "warrants": [
        {
          "offenses": [
            "Drug Court Commitment"
          ],
          "iceHold": "",
          "mugshotImage": "http://mugshots.bcgov.net/images/33/27433/24031918230000.jpeg",
          "arrestAgency": "Probation Parole",
          "arrestOfficer": "BLACK, T"
        }
      ]
    },
    {
      "name": {
        "last": "ORTIZ",
        "first": "JOSE",
        "middle": "MARIA-PEREZ"
      },
      "address": {
        "street": "137 CORDILLO PKWY",
        "cityStateZip": "hilton head, SC 29926"
      },
      "raceGender": "H-White/Latin, Hispanic / Male",
      "race": "L",
      "sex": "M",
      "dob": "12/29/92",
      "age": "31",
      "height": "5'11\"",
      "weight": "190",
      "bookingDate": "21:23:21 03/20/24",
      "bookingNumber": "46766",
      "warrants": [
        {
          "offenses": [
            "FUG. FROM JUSTICE WARRANT; NON-CRIM. HOLD FUG. MAX. 20 DAYS. GOV. OFC."
          ],
          "iceHold": "",
          "mugshotImage": "http://mugshots.bcgov.net/images/53/363353/",
          "arrestAgency": "Beaufort County Sheriff's Ofc",
          "arrestOfficer": "Seronka, Chad"
        }
      ]
    },
    {
      "name": {
        "last": "PATTERSON",
        "first": "LAKEEMA",
        "middle": "DIONSHA"
      },
      "address": {
        "street": "889 MID WAY CIR",
        "cityStateZip": "RIDGELAND, SC 29936"
      },
      "raceGender": "N-Black, Non-Hisp / Female",
      "race": "B",
      "sex": "F",
      "dob": "07/26/94",
      "age": "29",
      "height": "5'02\"",
      "weight": "170",
      "bookingDate": "15:28:27 03/18/24",
      "bookingNumber": "46724",
      "warrants": [
        {
          "offenses": [
            "HABITUAL OFFENDER VIOLATION"
          ],
          "iceHold": "",
          "mugshotImage": "http://mugshots.bcgov.net/images/24/45024/24031815410400.jpeg",
          "arrestAgency": "Bluffton PD",
          "arrestOfficer": ""
        }
      ]
    },
    {
      "name": {
        "last": "PIERCE",
        "first": "JODY",
        "middle": "WAYNE"
      },
      "address": {
        "street": "671 FARMLAKE DRIVE",
        "cityStateZip": "Bluffton, SC 29910"
      },
      "raceGender": "N-White, Non-Hisp / Male",
      "race": "W",
      "sex": "M",
      "dob": "12/02/66",
      "age": "57",
      "height": "5'10\"",
      "weight": "155",
      "bookingDate": "15:11:48 03/20/24",
      "bookingNumber": "46758",
      "warrants": [
        {
          "offenses": [
            "Family Court Bench Warrant"
          ],
          "iceHold": "",
          "mugshotImage": "http://mugshots.bcgov.net/images/71/49071/24032015170100.jpeg",
          "arrestAgency": "Beaufort County Sheriff's Ofc",
          "arrestOfficer": "Jennings, M"
        }
      ]
    },
    {
      "name": {
        "last": "POLANCO",
        "first": "SHAYNA",
        "middle": "MICHELLE"
      },
      "address": {
        "street": "2724 BRANTLEY RD",
        "cityStateZip": "KANNAPOLIS, NC 28083"
      },
      "raceGender": "N-White, Non-Hisp / Female",
      "race": "W",
      "sex": "F",
      "dob": "04/15/87",
      "age": "36",
      "height": "5'07\"",
      "weight": "155",
      "bookingDate": "20:24:34 03/20/24",
      "bookingNumber": "46765",
      "warrants": [
        {
          "offenses": [
            "In-State Hold"
          ],
          "iceHold": "",
          "mugshotImage": "http://mugshots.bcgov.net/images/78/363378/24032020253200.jpeg",
          "arrestAgency": "Beaufort County Sheriff's Ofc",
          "arrestOfficer": "Lacey, Th"
        }
      ]
    },
    {
      "name": {
        "last": "RAGLAND",
        "first": "TURNER",
        "middle": "SAVION"
      },
      "address": {
        "street": "8 BRYANT RD",
        "cityStateZip": "Hilton Head Isl, SC 29926"
      },
      "raceGender": "N-Black, Non-Hisp / Male",
      "race": "B",
      "sex": "M",
      "dob": "05/11/99",
      "age": "24",
      "height": "6'02\"",
      "weight": "185",
      "bookingDate": "04:35:53 03/20/24",
      "bookingNumber": "46749",
      "warrants": [
        {
          "offenses": [
            "DRIVING UNDER THE INFLUENCE (DUI)"
          ],
          "iceHold": "",
          "mugshotImage": "http://mugshots.bcgov.net/images/92/346892/24032004460900.jpeg",
          "arrestAgency": "Beaufort County Sheriff's Ofc",
          "arrestOfficer": "Erickson, M"
        }
      ]
    },
    {
      "name": {
        "last": "RAMOS-PEREZ",
        "first": "HENRY",
        "middle": "CARMELINO"
      },
      "address": {
        "street": "13 ABLE ST",
        "cityStateZip": "Bluffton, SC 29910"
      },
      "raceGender": "H-White/Latin, Hispanic / Male",
      "race": "L",
      "sex": "M",
      "dob": "08/20/97",
      "age": "26",
      "height": "5'02\"",
      "weight": "130",
      "bookingDate": "03:31:08 03/19/24",
      "bookingNumber": "46730",
      "warrants": [
        {
          "offenses": [
            "KIDNAPPING",
            "ICE Hold"
          ],
          "iceHold": "ICE Hold",
          "mugshotImage": "http://mugshots.bcgov.net/images/77/361977/24031903350600.jpeg",
          "arrestAgency": "Bluffton PD",
          "arrestOfficer": "Montero, L"
        }
      ]
    },
    {
      "name": {
        "last": "RICHARDSON",
        "first": "RAFAEL",
        "middle": "HAROLD"
      },
      "address": {
        "street": "11 PUTTERS LN",
        "cityStateZip": "ST HELENA IS, SC 29920 5812"
      },
      "raceGender": "N-Black, Non-Hisp / Male",
      "race": "B",
      "sex": "M",
      "dob": "05/25/01",
      "age": "22",
      "height": "5'06\"",
      "weight": "135",
      "bookingDate": "19:54:43 03/19/24",
      "bookingNumber": "46743",
      "warrants": [
        {
          "offenses": [
            "Probation and Parole Violation"
          ],
          "iceHold": "",
          "mugshotImage": "http://mugshots.bcgov.net/images/51/274451/24031920094500.jpeg",
          "arrestAgency": "Probation Parole",
          "arrestOfficer": "Fritz, R"
        }
      ]
    },
    {
      "name": {
        "last": "RODRIGUEZ-GARCIA",
        "first": "FERNANDO",
        "middle": "ADALID"
      },
      "address": {
        "street": "615 SHADY MARSH LN; SHADY GLEN",
        "cityStateZip": "BLUFFTON, SC 29910"
      },
      "raceGender": "H-White/Latin, Hispanic / Male",
      "race": "L",
      "sex": "M",
      "dob": "01/15/01",
      "age": "23",
      "height": "5'11\"",
      "weight": "185",
      "bookingDate": "10:32:33 03/21/24",
      "bookingNumber": "46778",
      "warrants": [
        {
          "offenses": [
            "Magistrate Bench Warrant"
          ],
          "iceHold": "",
          "mugshotImage": "http://mugshots.bcgov.net/images/88/58388/24032110565100.jpeg",
          "arrestAgency": "Beaufort County Sheriff's Ofc",
          "arrestOfficer": "Perkins, M"
        }
      ]
    },
    {
      "name": {
        "last": "SCHULTZ",
        "first": "CHAD",
        "middle": "WESTLEY"
      },
      "address": {
        "street": "514 33RD AVE N APT B",
        "cityStateZip": "MYRTLE BEACH, SC 295772914"
      },
      "raceGender": "N-White, Non-Hisp / Male",
      "race": "W",
      "sex": "M",
      "dob": "08/03/86",
      "age": "37",
      "height": "5'05\"",
      "weight": "200",
      "bookingDate": "02:10:43 03/20/24",
      "bookingNumber": "46746",
      "warrants": [
        {
          "offenses": [
            "PUBLIC DISORDERLY CONDUCT"
          ],
          "iceHold": "",
          "mugshotImage": "http://mugshots.bcgov.net/images/98/363298/",
          "arrestAgency": "Beaufort County Sheriff's Ofc",
          "arrestOfficer": "Cochenour, A"
        }
      ]
    },
    {
      "name": {
        "last": "SCHULTZ",
        "first": "CODY",
        "middle": "JARRETT"
      },
      "address": {
        "street": "4720 COTTONWOOD DR",
        "cityStateZip": "MYRTLE BEACH, SC 295887116"
      },
      "raceGender": "N-White, Non-Hisp / Male",
      "race": "W",
      "sex": "M",
      "dob": "07/11/91",
      "age": "32",
      "height": "5'11\"",
      "weight": "211",
      "bookingDate": "00:47:33 03/20/24",
      "bookingNumber": "46747",
      "warrants": [
        {
          "offenses": [
            "PUBLIC DISORDERLY CONDUCT"
          ],
          "iceHold": "",
          "mugshotImage": "http://mugshots.bcgov.net/images/00/363300/24032000495300.jpeg",
          "arrestAgency": "Beaufort County Sheriff's Ofc",
          "arrestOfficer": "Cochenour, A"
        }
      ]
    },
    {
      "name": {
        "last": "SCOTT",
        "first": "KASSIM",
        "middle": "SAHLE"
      },
      "address": {
        "street": "1376 FORDING ISLAND RD #165",
        "cityStateZip": "Bluffton, SC 29926"
      },
      "raceGender": "N-Black, Non-Hisp / Male",
      "race": "B",
      "sex": "M",
      "dob": "12/06/01",
      "age": "22",
      "height": "5'11\"",
      "weight": "146",
      "bookingDate": "21:03:21 03/18/24",
      "bookingNumber": "46725",
      "warrants": [
        {
          "offenses": [
            "DOMESTIC VIOLENCE 3RD DEGREE"
          ],
          "iceHold": "",
          "mugshotImage": "http://mugshots.bcgov.net/images/99/328399/24031821574200.jpeg",
          "arrestAgency": "Beaufort County Sheriff's Ofc",
          "arrestOfficer": "Walker, D"
        }
      ]
    },
    {
      "name": {
        "last": "SCOTT",
        "first": "LASHAWN",
        "middle": "GABRIEL"
      },
      "address": {
        "street": "15 SANDY LN; MARY II",
        "cityStateZip": "Ladys Island, SC"
      },
      "raceGender": "N-Black, Non-Hisp / Male",
      "race": "B",
      "sex": "M",
      "dob": "04/24/80",
      "age": "43",
      "height": "5'10\"",
      "weight": "180",
      "bookingDate": "00:10:38 03/19/24",
      "bookingNumber": "46728",
      "warrants": [
        {
          "offenses": [
            "DOMESTIC VIOLENCE 3RD DEGREE"
          ],
          "iceHold": "",
          "mugshotImage": "http://mugshots.bcgov.net/images/12/19512/24031900424400.jpeg",
          "arrestAgency": "Beaufort County Sheriff's Ofc",
          "arrestOfficer": "Phillips, D"
        }
      ]
    },
    {
      "name": {
        "last": "SEWARD",
        "first": "DEVAN",
        "middle": "ALEXANDER"
      },
      "address": {
        "street": "4921 BLUFFTON PKWY #767",
        "cityStateZip": "Bluffton, SC 29910"
      },
      "raceGender": "Unknown / Male",
      "race": "U",
      "sex": "M",
      "dob": "05/17/95",
      "age": "28",
      "height": "6'02\"",
      "weight": "190",
      "bookingDate": "09:56:03 03/19/24",
      "bookingNumber": "46742",
      "warrants": [
        {
          "offenses": [
            "DRIVING WITHOUT A LICENSE OR POSSESSION OF MORE THAN ONE DRIVERS LICENSE"
          ],
          "iceHold": "",
          "mugshotImage": "http://mugshots.bcgov.net/images/90/264690/22120508580600.jpeg",
          "arrestAgency": "Beaufort County Sheriff's Ofc",
          "arrestOfficer": ""
        }
      ]
    },
    {
      "name": {
        "last": "SHULER",
        "first": "JUSTIN",
        "middle": "AMAD"
      },
      "address": {
        "street": "6786 W FRONTAGE RD",
        "cityStateZip": "COOSAWHATCHIE, SC 29912"
      },
      "raceGender": "N-Black, Non-Hisp / Male",
      "race": "B",
      "sex": "M",
      "dob": "10/29/01",
      "age": "22",
      "height": "5'06\"",
      "weight": "195",
      "bookingDate": "08:34:35 03/21/24",
      "bookingNumber": "46776",
      "warrants": [
        {
          "offenses": [
            "RECKLESS DRIVING",
            "DRIVING UNDER SUSPENSION; LICENSE SUSPENDED FOR DUI - 3RD OR SUB. OFFENSE",
            "HABITUAL TRAFFIC OFFENDERS; DUS AS PER HABITUAL TRAFFIC OFFENDER STATUS"
          ],
          "iceHold": "",
          "mugshotImage": "http://mugshots.bcgov.net/images/97/119397/24032108373500.jpeg",
          "arrestAgency": "Beaufort County Sheriff's Ofc",
          "arrestOfficer": "Goodson, D"
        }
      ]
    },
    {
      "name": {
        "last": "SIMMONS",
        "first": "D'ANTAE",
        "middle": "JI-MEER"
      },
      "address": {
        "street": "32 WILLIAM DR",
        "cityStateZip": "Hilton Head Isl, SC 29926"
      },
      "raceGender": "N-Black, Non-Hisp / Male",
      "race": "B",
      "sex": "M",
      "dob": "06/23/05",
      "age": "18",
      "height": "6'01\"",
      "weight": "155",
      "bookingDate": "13:32:53 03/20/24",
      "bookingNumber": "46756",
      "warrants": [
        {
          "offenses": [
            "Fleeing to evade arrest or detention"
          ],
          "iceHold": "",
          "mugshotImage": "http://mugshots.bcgov.net/images/43/215743/24032013404800.jpeg",
          "arrestAgency": "Beaufort County Sheriff's Ofc",
          "arrestOfficer": "Snyder, R"
        }
      ]
    },
    {
      "name": {
        "last": "SMITH",
        "first": "ALYSSA",
        "middle": "GRACE JANE"
      },
      "address": {
        "street": "606 CARTERET ST APT 3",
        "cityStateZip": "BEAUFORT, SC 29902 5067"
      },
      "raceGender": "N-Black, Non-Hisp / Female",
      "race": "B",
      "sex": "F",
      "dob": "12/09/02",
      "age": "21",
      "height": "5'03\"",
      "weight": "138",
      "bookingDate": "01:04:30 03/19/24",
      "bookingNumber": "46729",
      "warrants": [
        {
          "offenses": [
            "Marij: Simple Possession"
          ],
          "iceHold": "",
          "mugshotImage": "http://mugshots.bcgov.net/images/65/116165/",
          "arrestAgency": "Beaufort County Sheriff's Ofc",
          "arrestOfficer": "Takais, G"
        }
      ]
    },
    {
      "name": {
        "last": "STAFFORD",
        "first": "GIONNA",
        "middle": "ANN"
      },
      "address": {
        "street": "97 WILLAIM HILTON PKWY",
        "cityStateZip": "HILTON HEAD ISL, SC 29926"
      },
      "raceGender": "N-Black, Non-Hisp / Female",
      "race": "B",
      "sex": "F",
      "dob": "03/07/99",
      "age": "25",
      "height": "5'09\"",
      "weight": "190",
      "bookingDate": "09:43:04 03/20/24",
      "bookingNumber": "46753",
      "warrants": [
        {
          "offenses": [
            "Marij/Poss 28g<10gr<Hash 1st"
          ],
          "iceHold": "",
          "mugshotImage": "http://mugshots.bcgov.net/images/83/108983/",
          "arrestAgency": "Beaufort County Sheriff's Ofc",
          "arrestOfficer": "Goodson, D"
        }
      ]
    },
    {
      "name": {
        "last": "VELASQUEZ-VARELA",
        "first": "RICARDO",
        "middle": "ISAI"
      },
      "address": {
        "street": "491 LIVE OAK WALK; EDGEFIELD",
        "cityStateZip": "Bluffton, SC 29910"
      },
      "raceGender": "H-White/Latin, Hispanic / Male",
      "race": "L",
      "sex": "M",
      "dob": "02/03/02",
      "age": "22",
      "height": "5'11\"",
      "weight": "152",
      "bookingDate": "21:42:54 03/19/24",
      "bookingNumber": "46745",
      "warrants": [
        {
          "offenses": [
            "DRIVING WITHOUT A LICENSE OR POSSESSION OF MORE THAN ONE DRIVERS LICENSE"
          ],
          "iceHold": "",
          "mugshotImage": "http://mugshots.bcgov.net/images/10/150210/24031921083700.jpeg",
          "arrestAgency": "South Carolina Highway Patrol",
          "arrestOfficer": "CLARKSON"
        }
      ]
    },
    {
      "name": {
        "last": "WANG",
        "first": "JONATHAN",
        "middle": "TIANEN"
      },
      "address": {
        "street": "27 WOODPARK CIR",
        "cityStateZip": "LEXINGTON, MA 02421"
      },
      "raceGender": "N-Asian/Pacific Islander, Non- / Male",
      "race": "A",
      "sex": "M",
      "dob": "08/24/00",
      "age": "23",
      "height": "6'00\"",
      "weight": "180",
      "bookingDate": "22:31:13 03/20/24",
      "bookingNumber": "46767",
      "warrants": [
        {
          "offenses": [
            "PUBLIC DISORDERLY CONDUCT"
          ],
          "iceHold": "",
          "mugshotImage": "http://mugshots.bcgov.net/images/80/363380/24032022452100.jpeg",
          "arrestAgency": "Beaufort County Sheriff's Ofc",
          "arrestOfficer": "Cochenour, A"
        }
      ]
    },
    {
      "name": {
        "last": "WASHINGTON",
        "first": "CHARLES",
        "middle": ""
      },
      "address": {
        "street": "1005 NEWCASTLE ST",
        "cityStateZip": "BEAUFORT, SC 29910"
      },
      "raceGender": "N-Black, Non-Hisp / Male",
      "race": "B",
      "sex": "M",
      "dob": "10/30/56",
      "age": "67",
      "height": "5'06\"",
      "weight": "160",
      "bookingDate": "22:07:39 03/18/24",
      "bookingNumber": "46727",
      "warrants": [
        {
          "offenses": [
            "Appearing Drunk on Streets"
          ],
          "iceHold": "",
          "mugshotImage": "http://mugshots.bcgov.net/images/91/138491/24031823045000.jpeg",
          "arrestAgency": "Beaufort PD",
          "arrestOfficer": "Humphries, M"
        }
      ]
    },
    {
      "name": {
        "last": "WEBB",
        "first": "LARON",
        "middle": "LAMAR"
      },
      "address": {
        "street": "120 BRUCE K SMALLS DR",
        "cityStateZip": "Grays Hill, SC 29906"
      },
      "raceGender": "N-Black, Non-Hisp / Male",
      "race": "B",
      "sex": "M",
      "dob": "04/05/76",
      "age": "47",
      "height": "5'10\"",
      "weight": "185",
      "bookingDate": "08:24:23 03/19/24",
      "bookingNumber": "46733",
      "warrants": [
        {
          "offenses": [
            "Family Court Bench Warrant",
            "Family Court Bench Warrant",
            "Family Court Bench Warrant"
          ],
          "iceHold": "",
          "mugshotImage": "http://mugshots.bcgov.net/images/15/25815/24031908433500.jpeg",
          "arrestAgency": "Beaufort County Sheriff's Ofc",
          "arrestOfficer": "Malphrus, D"
        }
      ]
    },
    {
      "name": {
        "last": "WIGAL",
        "first": "ROBERT",
        "middle": "MARION"
      },
      "address": {
        "street": "13 FAIRWOOD AVE",
        "cityStateZip": "BLUFFTON, SC 29910 7231"
      },
      "raceGender": "N-White, Non-Hisp / Male",
      "race": "W",
      "sex": "M",
      "dob": "06/26/90",
      "age": "33",
      "height": "6'01\"",
      "weight": "165",
      "bookingDate": "12:02:14 03/20/24",
      "bookingNumber": "46754",
      "warrants": [
        {
          "offenses": [
            "Family Court Commitment"
          ],
          "iceHold": "",
          "mugshotImage": "http://mugshots.bcgov.net/images/04/248104/24032012233900.jpeg",
          "arrestAgency": "Beaufort County Sheriff's Ofc",
          "arrestOfficer": "Parnell, R"
        }
      ]
    },
    {
      "name": {
        "last": "WILLIAMS",
        "first": "GARY",
        "middle": "PETE"
      },
      "address": {
        "street": "361 HAMILTON LN",
        "cityStateZip": "YEMASSEE, SC 29945"
      },
      "raceGender": "N-Black, Non-Hisp / Male",
      "race": "B",
      "sex": "M",
      "dob": "11/26/80",
      "age": "43",
      "height": "5'06\"",
      "weight": "160",
      "bookingDate": "15:24:05 03/19/24",
      "bookingNumber": "46737",
      "warrants": [
        {
          "offenses": [
            "Family Court Bench Warrant",
            "Family Court Bench Warrant"
          ],
          "iceHold": "",
          "mugshotImage": "http://mugshots.bcgov.net/images/25/11825/24031915470400.jpeg",
          "arrestAgency": "Beaufort County Sheriff's Ofc",
          "arrestOfficer": "Snyder, R"
        }
      ]
    }
  ]
}